Workbook

Sheet Input
A1: Name of the companies | B1: Mkt Cap | C1: CP | D1: ROCE | E1: Stock P/E | F1: ROE | G1: OPM% | H1: Sales | I1: NP | J1: Revenue CAGR | K1: Profit CAGR | L1: CFO | M1: PEG | N1: Debtor days | O1: NPM
A3: Workmates Core2Cloud | B3: 469 | C3: 363 | D3: 0.923 | E3: 29.2 | F3: 0.875 | G3: 0.16 | H3: 134 | I3: 16 | J3: 1.04 | K3: 1.23 | L3: 5 | M3: =(E3/K3)/100 -> 0.23739837 | N3: 84 | O3: =I3/H3*100 -> 11.940299
A4: TechD Cybersecurity | B4: 442 | C4: 591 | D4: 0.815 | E4: 46.8 | F4: 0.62 | G4: 0.38 | H4: 18 | I4: 6 | J4: 1.32 | K4: 1.94 | L4: -2 | M4: =(E4/K4)/100 -> 0.24123711 | N4: 154 | O4: =I4/H4*100 -> 33.333333
A5: Namo eWaste Management Ltd | B5: 420 | C5: 184 | D5: 0.191 | E5: 41.5 | F5: 0.138 | G5: 0.1 | H5: 170 | I5: 10 | J5: 0.29 | K5: 0.07 | L5: -20 | M5: =(E5/K5)/100 -> 5.9285714 | N5: 31 | O5: =I5/H5*100 -> 5.8823529
A6: Chatha Foods Ltd | B6: 218 | C6: 90.5 | D6: 0.119 | E6: 36.2 | F6: 0.0864 | G6: 0.07 | H6: 167 | I6: 6 | J6: 0.22 | K6: 0.01 | L6: -1 | M6: =(E6/K6)/100 -> 36.2 | N6: 53 | O6: =I6/H6*100 -> 3.5928144
A7: Yash Highvoltage Ltd | B7: 1731 | C7: 606 | D7: 0.285 | E7: 59.6 | F7: 0.226 | G7: 0.22 | H7: 193 | I7: 29 | J7: 0.65 | K7: 0.35 | L7: 9 | M7: =(E7/K7)/100 -> 1.7028571 | N7: 68 | O7: =I7/H7*100 -> 15.025907
A8: Sunlite Recycling Industries Ltd | B8: 643 | C8: 466 | D8: 0.361 | E8: 29.8 | F8: 0.36 | G8: 0.02 | H8: 1882 | I8: 22 | J8: 0.57 | K8: 0.82 | L8: 8 | M8: =(E8/K8)/100 -> 0.36341463 | N8: 5 | O8: =I8/H8*100 -> 1.1689692
A9: Paradeep Parivahan Ltd | B9: 223 | C9: 140 | D9: 0.237 | E9: 6.3 | F9: 0.262 | G9: 0.15 | H9: 178 | I9: 16 | J9: 0.21 | K9: 1.07 | L9: 4 | M9: =(E9/K9)/100 -> 0.058878505 | N9: 98 | O9: =I9/H9*100 -> 8.988764
A10: Silkflex Polymers (India) Ltd | B10: 170 | C10: 147 | D10: 0.241 | E10: 18.1 | F10: 0.292 | G10: 0.1495 | H10: 80.13 | I10: 7 | J10: 0.42 | K10: 1.16 | L10: -30.23 | M10: =(E10/K10)/100 -> 0.15603448 | N10: 46 | O10: =I10/H10*100 -> 8.7358043

Sheet View data
A1: Name of the Company | B1: CFO | C1: Net profit margin | D1: OPM% | E1: ROCE | F1: ROE | G1: Profit CAGR | H1: Revenue CAGR | I1: P/E | J1: PEG | K1: Debtor Days
A2: Workmates Core2Cloud | B2: =Input!L3 -> 5 | C2: =Input!O3 -> 11.940299 | D2: =Input!G3 -> 0.16 | E2: =Input!D3 -> 0.923 | F2: =Input!F3 -> 0.875 | G2: =Input!K3 -> 1.23 | H2: =Input!J3 -> 1.04 | I2: =Input!E3 -> 29.2 | J2: =(I2/G2)/100 -> 0.23739837 | K2: =Input!N3 -> 84
A3: TechD Cybersecurity | B3: =Input!L4 -> -2 | C3: =Input!O4 -> 33.333333 | D3: =Input!G4 -> 0.38 | E3: =Input!D4 -> 0.815 | F3: =Input!F4 -> 0.62 | G3: =Input!K4 -> 1.94 | H3: =Input!J4 -> 1.32 | I3: =Input!E4 -> 46.8 | J3: =(I3/G3)/100 -> 0.24123711 | K3: =Input!N4 -> 154
A4: Namo eWaste Management Ltd | B4: =Input!L5 -> -20 | C4: =Input!O5 -> 5.8823529 | D4: =Input!G5 -> 0.1 | E4: =Input!D5 -> 0.191 | F4: =Input!F5 -> 0.138 | G4: =Input!K5 -> 0.07 | H4: =Input!J5 -> 0.29 | I4: =Input!E5 -> 41.5 | J4: =(I4/G4)/100 -> 5.9285714 | K4: =Input!N5 -> 31
A5: Chatha Foods Ltd | B5: =Input!L6 -> -1 | C5: =Input!O6 -> 3.5928144 | D5: =Input!G6 -> 0.07 | E5: =Input!D6 -> 0.119 | F5: =Input!F6 -> 0.0864 | G5: =Input!K6 -> 0.01 | H5: =Input!J6 -> 0.22 | I5: =Input!E6 -> 36.2 | J5: =(I5/G5)/100 -> 36.2 | K5: =Input!N6 -> 53
A6: Yash Highvoltage Ltd | B6: =Input!L7 -> 9 | C6: =Input!O7 -> 15.025907 | D6: =Input!G7 -> 0.22 | E6: =Input!D7 -> 0.285 | F6: =Input!F7 -> 0.226 | G6: =Input!K7 -> 0.35 | H6: =Input!J7 -> 0.65 | I6: =Input!E7 -> 59.6 | J6: =(I6/G6)/100 -> 1.7028571 | K6: =Input!N7 -> 68
A7: Sunlite Recycling Industries Ltd | B7: =Input!L8 -> 8 | C7: =Input!O8 -> 1.1689692 | D7: =Input!G8 -> 0.02 | E7: =Input!D8 -> 0.361 | F7: =Input!F8 -> 0.36 | G7: =Input!K8 -> 0.82 | H7: =Input!J8 -> 0.57 | I7: =Input!E8 -> 29.8 | J7: =(I7/G7)/100 -> 0.36341463 | K7: =Input!N8 -> 5
A8: Paradeep Parivahan Ltd | B8: =Input!L9 -> 4 | C8: =Input!O9 -> 8.988764 | D8: =Input!G9 -> 0.15 | E8: =Input!D9 -> 0.237 | F8: =Input!F9 -> 0.262 | G8: =Input!K9 -> 1.07 | H8: =Input!J9 -> 0.21 | I8: =Input!E9 -> 6.3 | J8: =(I8/G8)/100 -> 0.058878505 | K8: =Input!N9 -> 98
A9: Silkflex Polymers (India) Ltd | B9: =Input!L10 -> -30.23 | C9: =Input!O10 -> 8.7358043 | D9: =Input!G10 -> 0.1495 | E9: =Input!D10 -> 0.241 | F9: =Input!F10 -> 0.292 | G9: =Input!K10 -> 1.16 | H9: =Input!J10 -> 0.42 | I9: =Input!E10 -> 18.1 | J9: =(I9/G9)/100 -> 0.15603448 | K9: =Input!N10 -> 46

Sheet Workmates Core2Cloud
A1: Business Quality
A2: How does the company make money? | B2: This is IT service company that provides AWS services for monthly/annual subscription and selling technical expertise.
A3: Who is the customer? | B3: Mid-Large enterprices that want to shift to cloud based services
A4: Why would the customer choose them over others? | B4: AWS Premier Partner which is one of the highest tiers AWS awards
A6: Edge
A7: What makes this company different? | B7: WS Premier Partner status is real and verified by AWS annually. It requires a minimum number of AWS-certified engineers, proven customer deployments, and passing AWS audits
A8: Can competitors easily copy this? | B8: Yes but also no. Any IT company can start the journey but becoming AWS partner takes 3-5 years
A9: Does it have:
A10: Pricing power? | B10: Not really, very competitive BUT Premier Partner status allows them to charge a premium over basic AWS resellers
A11: Switching costs? | B11: More than meets the eye since switching to different managed service provider means re-migrating configs. and that risks downtime. Risky for large businesses
A12: Brand? | B12: Very small
A13: Tech advantage? | B13: None. It USES tech, doesn't own it
A15: Growth Filter
A16: Is revenue growing consistently over 3–5 years? | B16: Yes, very fast. Clean, consistent doubling every year for 3 consecutive years
A17: Is profit growing faster than revenue? | B17: Yes. Revenue CAGR 3yr = 103%, Profit CAGR 3yr = 141%. Profit is growing faster. Margins went from 14% to 16-17%. Operating leverage is working.
A18: What's driving growth? volume, price, new customers, or just accounting? | B18: More clients, more projects, more hiring. Employee growth was 54%
A20: Risks
A21: Is debt dangerously high relative to earnings? | B21: No. Borrowings = ₹9 Cr, Net Profit TTM = ₹16 Cr. Debt is less than one year's profit. Very manageable.
A22: What breaks this business? | B22: Loss of key clients, Talent risk, AWS partnernship, no pricing power, Cashflow stress
A24: My Interests
A25: Will this make me money? | B25: Yes, with high probability over 2-3 years. P/E is 29x
A26: Is this a good business? | B26: Moderately good. Not exceptional like other companies which has a manufacturing moat.
A27: If the stock falls 30% after you buy @ CMP, what will you do?:
A28: Sell? Hold? Buy more? | B28: Buy more.
A29: WHY? | B29: Why? If stock falls from 363 to 254 then I'm getting the same growth but at cheaper price. A price movement alone is not a problem.

Sheet TechD Cybersecurity
A1: Business Quality
A2: How does the company make money? | B2: Cybersecurity services company. Earns money through three streams - Security audits and compliance checks, managed security operations centre and training/certificates
A3: Who is the customer? | B3: Large enterprises across BFSI, manufacturing, healthcare, aviation, IT, and government. Known clients include Adani Group, Zensar Technologies, Astral Limited. Also international clients like ETO GRUPPE Technologies (Germany) and IQM Corporation.
A4: Why would the customer choose them over others? | B4: CERT-In, a government of India certification that authorises them to conduct cybersecurity audits for critical infrastructure
A6: Edge
A7: What makes this company different? | B7: CERT-In empanelment is the real differentiator. It's not self-declared. The Indian government validates it. Companies without this cannot serve government and regulated sector clients
A8: Can competitors easily copy this? | B8: CERT-in empanelment takes years of proven track record and govt. validation. Not something anyone can get easily. Requires significant capital investment
A9: Does it have:
A10: Pricing power? | B10: Yes. CERT-In empanelled firms can charge premium rates especially for government contracts. Cybersecurity is also non-discretionary spending for large enterprises
A11: Switching costs? | B11: High. A company running its entire security operations through TechD's SOC cannot easily switch
A12: Brand? | B12: Small but growing. Known within cybersecurity circles, not mainstream.
A13: Tech advantage? | B13: Moderate. They have partnerships with Securonix and Seceon for advanced threat detection tools. These OEM partnerships give them technology they couldn't build themselves.
A15: Growth Filter
A16: Is revenue growing consistently over 3–5 years? | B16: Yes. Consistent and accelerating.
A17: Is profit growing faster than revenue? | B17: Yes. Revenue CAGR 3yr = 132%, Profit CAGR 3yr = 194%. Profit growing significantly faster. Operating margins expanded dramatically from 4% to 38-49%, massive operating leverage.
A18: What's driving growth? volume, price, new customers, or just accounting? | B18: New enterprise clients, expanding SOC services, government contract wins, and geographic expansion including international clients
A20: Risks
A21: Is debt dangerously high relative to earnings? | B21: No. Zero borrowings as of Mar 2025 and Sep 2025. Completely debt free.
A22: What breaks this business? | B22: Clients not paying (debtor days at 154, if worsens then cash crisis could happen. CERT-In empanelment revoked. Cybersecurity breach at a major client. Key personnel leaving.
A24: My Interests
A25: Will this make me money? | B25: Uncertain. The business is exceptional but cash flow problem creates real risk. If CFO turns positive in FY26 the stock could re-rate sharply upward. If CFO stays negative the market will eventually punish it. High risk, high reward.
A26: Is this a good business? | B26: Yes! CERT-In moat, zero debt, 194% profit CAGR. The business model is genuinely strong.
A27: If the stock falls 30% after you buy @ CMP, what will you do?:
A28: Sell? Hold? Buy more? | B28: Hold and monitor
A29: WHY? | B29: Negative CFO is a problem. I would wait for the next quarter and if CFO turns positive then buy more otherwise sell regardless of price

Sheet Namo eWaste Management Ltd
A1: Business Quality
A2: How does the company make money? | B2: E-waste recycling company. Collects old electronics - phones, laptops, ACs, refrigerators - from corporates and individuals, disassembles them, extracts valuable materials like copper, gold, and plastics, and sells these recovered materials. Also provides ITAD (IT Asset Disposition) services to corporates - securely wiping and disposing of old IT equipment
A3: Who is the customer? | B3: Corporates disposing of old IT equipment who need data security and compliance certificates and electronics manufacturers who need Extended Producer Responsibility (EPR) compliance.
A4: Why would the customer choose them over others? | B4: ISO certified recycler. EPR authorisation from government - mandatory for legal compliance. Corporates specifically need certified recyclers to get compliance certificates for their ESG reporting.
A6: Edge
A7: What makes this company different? | B7: EPR authorisation and ISO certification create a regulatory moat similar to TechD's CERT-In. Uncertified recyclers cannot provide the compliance certificates that corporates need
A8: Can competitors easily copy this? | B8: Getting EPR authorisation takes time and government approval. Building collection logistics infrastructure takes years. So moderately difficult to copy in the short term.
A9: Does it have:
A10: Pricing power? | B10: Low. E-waste recycling is driven by commodity prices of recovered materials - copper, gold, aluminium. When commodity prices fall, recovery value falls and margins compress. Limited ability to raise prices.
A11: Switching costs? | B11: Low to moderate. Corporates can switch recyclers relatively easily if another certified recycler offers better rates.
A12: Brand? | B12: Very small. Not known outside compliance circles.
A13: Tech advantage? | B13: None meaningful.
A15: Growth Filter
A16: Is revenue growing consistently over 3–5 years? | B16: Yes but slowly.
A17: Is profit growing faster than revenue? | B17: No. Revenue grew 29% TTM but profit grew only 7% TTM. Costs are eating into growth.
A18: What's driving growth? volume, price, new customers, or just accounting? | B18: Government EPR mandates forcing more corporates to use certified recyclers. Volume driven not price driven.
A20: Risks
A21: Is debt dangerously high relative to earnings? | B21: No. Borrowings reduced to 3Cr. Very good
A22: What breaks this business? | B22: If material prices fall then the recovery value drops. CFO was negative and if it continues then it'll need to raise debt or equity.
A24: My Interests
A25: Will this make me money? | B25: Unlikely at current price. Paying 41.5x earnings for 7% profit growth is not a good decision. Risk of loss is higher than chance of meaningful gain at current price.
A26: Is this a good business? | B26: Mediocre. Real regulatory tailwind from EPR mandates but margins are thin, commodity-dependent, and cash flow has deteriorated sharply. Not a compounding business.
A27: If the stock falls 30% after you buy @ CMP, what will you do?:
A28: Sell? Hold? Buy more? | B28: Sell
A29: WHY? | B29: Because the thesis was already weak at purchase price. A 30% fall would put it at roughly 29x P/E for 7% growth. Still not a good buy.

Sheet Chatha Foods Ltd
A1: Business Quality
A2: How does the company make money? | B2: Frozen and ready-to-eat food manufacturer. Makes burger patties, pizza toppings, sandwich fillings, kebabs, nuggets, and plant-based meat alternatives. Sells exclusively B2B to Quick Service Restaurants (QSRs) like Dominos, cafes, and hotel chains
A3: Who is the customer? | B3: SR chains, casual dining restaurants, hotels, cafeterias. Institutional bulk buyers who need consistent supply of frozen processed food.
A4: Why would the customer choose them over others? | B4: Established supplier relationships with major QSR chains. Cold chain infrastructure and food safety certifications.
A6: Edge
A7: What makes this company different? | B7: The Allana JV is the one potentially interesting development. Allana has massive cold chain infrastructure and export relationships.
A8: Can competitors easily copy this? | B8: Yes. Frozen food manufacturing is not technically complex. Any food processor with the right equipment can make burger patties. The real barrier is QSR supplier approval processes which take time but are not impossible.
A9: Does it have:
A10: Pricing power? | B10: Very low. QSR chains are powerful buyers who squeeze suppliers on price. Chatha has no brand with end consumers so they have zero pricing power in the supply chain.
A11: Switching costs? | B11: Low. QSR chains regularly dual-source and can switch frozen food suppliers with 3-6 months notice. No technology lock-in, no certification dependency.
A12: Brand? | B12: Zero with consumers
A13: Tech advantage? | B13: None
A15: Growth Filter
A16: Is revenue growing consistently over 3–5 years? | B16: Inconsistently. Revenue actually fell from 91 Cr in FY19 to 61 Cr in FY21. Then recovered. Current revenue 167 Cr TTM - but took 5 years to get here from 91 Cr. That is very slow progress for a 28-year-old company.
A17: Is profit growing faster than revenue? | B17: No. Revenue grew 22% over 3 years but profit grew only 1% TTM. Not a good look for a 28 years old company
A18: What's driving growth? volume, price, new customers, or just accounting? | B18: Mostly volume - more QSR outlets opening across India is lifting overall demand
A20: Risks
A21: Is debt dangerously high relative to earnings? | B21: Mild concern. Borrowings back up to ₹21 Cr in Sep 2025 after being reduced. Net Profit only ₹6 Cr. Debt is 3.5x annual profit.
A22: What breaks this business? | B22: QSR chains consolidating suppliers and dropping Chatha. Plant based food trend not materialising. Promoters continue to sell
A24: My Interests
A25: Will this make me money? | B25: Very unlikely. For 1% profit growth we're paying 36x earnings
A26: Is this a good business? | B26: No. A 28-year-old company earning ₹6 Cr profit with declining promoter confidence, no pricing power, and a history of losses in FY21 is a poor business.
A27: If the stock falls 30% after you buy @ CMP, what will you do?:
A28: Sell? Hold? Buy more? | B28: Sell immediately.
A29: WHY? | B29: There is no thesis to hold onto. Profits are flat, promoters are selling, institutions have reduced, cash flow turned negative, and the business has no meaningful moat. A 30% fall is the market catching up to what the fundamentals have been saying for 3 years

Sheet Yash Highvoltage Ltd
A1: Business Quality
A2: How does the company make money? | B2: Manufactures transformer bushings - a critical component inside power transformers that allows high voltage electricity to pass safely through the transformer casing. Sells to transformer manufacturers, power utilities, and electrical equipment companies. Both domestic and international customers. B2B manufacturing business.
A3: Who is the customer? | B3: Transformer manufacturers (who then sell to power companies), direct sales to power utilities like state electricity boards, and industrial customers who operate large electrical equipment. International clients in Middle East, Southeast Asia, and Europe.
A4: Why would the customer choose them over others? | B4: Transformer bushings are technically complex - they must handle extremely high voltages without failure. A failed bushing can destroy an entire transformer worth crores. So buyers prioritise proven suppliers with track record over price. Yash has 20+ years of manufacturing experience and international certifications. Switching to a cheaper unknown supplier is too risky for buyers.
A6: Edge
A7: What makes this company different? | B7: Niche manufacturing with high technical barriers. Transformer bushings require specialised materials (Oil Impregnated Paper, Resin Impregnated Paper) and precision manufacturing. Very few Indian companies make high-voltage bushings at this quality level.
A8: Can competitors easily copy this? | B8: No. High voltage transformer bushing manufacturing requires specialised equipment, material science knowledge, and years of testing and certification. A new entrant would need 5-7 years minimum to reach comparable quality levels.
A9: Does it have:
A10: Pricing power? | B10: Yes. 20-22% operating margins sustained across multiple commodity and economic cycles proves genuine pricing power. Buyers cannot easily find alternatives so Yash can maintain prices.
A11: Switching costs? | B11: Very high. Once a transformer manufacturer qualifies Yash as an approved bushing supplier, switching requires re-qualification testing of a new supplier. Buyers would avoid this unless absolutely necessary
A12: Brand? | B12: Strong within the industry. Known internationally - they export to multiple countries which validates product quality independently.
A13: Tech advantage? | B13: Yes. Manufacturing know-how built over 20 years is a real technical advantage. Not software technology but deep materials and process knowledge that cannot be replicated without years of experience.
A15: Growth Filter
A16: Is revenue growing consistently over 3–5 years? | B16: Yes. Clean consistent growth accelerating in recent years driven by India's massive power infrastructure expansion.
A17: Is profit growing faster than revenue? | B17: Yes. Profit consistently outpacing revenue as operating leverage builds.
A18: What's driving growth? volume, price, new customers, or just accounting? | B18: India's power sector capex boom. Government is spending Crores on power transmission infrastructure. Every new transformer needs bushings.
A20: Risks
A21: Is debt dangerously high relative to earnings? | B21: Mild. Borrowings increased very little, about one year's profit.
A22: What breaks this business? | B22: Power sector capex slowdown. New well-funded competitor entering.
A24: My Interests
A25: Will this make me money? | B25: Possibly but with significant timing risk.
A26: Is this a good business? | B26: Yes. Genuine moat, best cash flows, strongest margins, clear structural demand tailwind. If you could buy it at 25-30x PE it would be an obvious selection.
A27: If the stock falls 30% after you buy @ CMP, what will you do?:
A28: Sell? Hold? Buy more? | B28: Hold
A29: WHY? | B29: The business fundamentals are intact - the moat is real, power sector capex is continuing, margins are stable. A 30% fall would bring PE from 59.6x to approximately 42x - still expensive but more justifiable. The problem is you'd be sitting on a 30% loss in a great business simply because you paid too much.

Sheet Sunlite Recycling Industries Lt
A1: Business Quality
A2: How does the company make money? | B2: Buys copper scrap, melts and processes it, and sells copper rods, wires, earthing strips, and conductors to electrical and power companies. Pure commodity processing business.
A3: Who is the customer? | B3: Electrical cable manufacturers, power transmission companies, and electronics manufacturers who need copper rods and wires as raw material for their own production.
A4: Why would the customer choose them over others? | B4: Price and reliability of supply. There is no technical differentiation - copper rod is copper rod. Customers choose whoever offers the best price with consistent quality and delivery.
A6: Edge
A7: What makes this company different? | B7: Nothing meaningful. ISO 9001 certification is table stakes in manufacturing. Location in Gujarat gives some logistics advantage for western India customers. That's it.
A8: Can competitors easily copy this? | B8: Yes completely. Copper recycling and rod manufacturing is not technically complex. Any company with the capital to buy the equipment can enter this business. There are already hundreds of competitors across India.
A9: Does it have:
A10: Pricing power? | B10: Zero. Copper is a globally traded commodity
A11: Switching costs? | B11: Zero. Copper rod is a commodity - buyers switch suppliers based purely on price. No certification dependency, no technical lock-in.
A12: Brand? | B12: Irrelevent
A13: Tech advantage? | B13: None
A15: Growth Filter
A16: Is revenue growing consistently over 3–5 years? | B16: Yes but only due to copper price inflation, not business improvement
A17: Is profit growing faster than revenue? | B17: Yes but not significant. On a 1882 Crore revenue earning only 22 crore profit.
A18: What's driving growth? volume, price, new customers, or just accounting? | B18: Higher copper prices globally inflating revenue, and volume expansion. Neither is a sustainable competitive advantage.
A20: Risks
A21: Is debt dangerously high relative to earnings? | B21: Manageable currently, 23 crore debt with 22 crore profit.
A22: What breaks this business? | B22: Copper price fall and key customers leaving
A24: My Interests
A25: Will this make me money? | B25: Unlikely to generate strong returns from here.
A26: Is this a good business? | B26: No. A business where raw materials are 96% of revenue and operating margins are 2% is structurally incapable of generating meaningful returns on capital over time.
A27: If the stock falls 30% after you buy @ CMP, what will you do?:
A28: Sell? Hold? Buy more? | B28: Sell
A29: WHY? | B29: There is no business quality to fall back on. The only reason to hold a 2% margin commodity processor is if you believe copper prices will keep rising. That's speculation, not investing.

Sheet Paradeep Parivahan Ltd
A1: Business Quality
A2: How does the company make money? | B2: Port logistics company operating exclusively inside Paradip Port in Odisha - one of India's largest ports handling coal, fertilisers, and bulk cargo. Revenue streams include cargo handling fees, intra-port transportation charges, stevedoring (loading and unloading ships), railway siding operations, warehousing, and crusher operations
A3: Who is the customer? | B3: Companies importing bulk cargo through Paradip Port
A4: Why would the customer choose them over others? | B4: They cannot easily choose someone else. Paradeep Parivahan operates within the port boundary under specific port authority agreements. A competing logistics company cannot simply set up operations inside the port without separate port authority approval - a process that takes years and is not guaranteed. This is a captive location moat.
A6: Edge
A7: What makes this company different? | B7: The port location is the entire moat. Being physically inside Paradip Port and holding operational rights within the port boundary means competitors cannot displace them without Paradip Port Trust cancelling their agreement and awarding it to someone else.
A8: Can competitors easily copy this? | B8: No. You cannot replicate being inside a specific port. A competitor would need to win a separate tender from Paradip Port Trust, build their own equipment inside the port, and prove operational capability - a process that would take 3-5 years minimum and is not guaranteed.
A9: Does it have:
A10: Pricing power? | B10: Moderate. Port tariffs are partly regulated but Paradeep Parivahan has some flexibility in negotiating rates with cargo owners, especially for specialised services like hazardous cargo handling and crusher operations.
A11: Switching costs? | B11: Very high for cargo owners. If a coal importer has been using Paradeep Parivahan's infrastructure at Paradip Port for years, switching to another handler means coordinating with the port authority, potentially losing berth priority, and risking operational disruptions. Cargo owners avoid switching.
A12: Brand? | B12: Strong within the port operations and bulk logistics industry. Known to all major importers using Paradip Port.
A13: Tech advantage? | B13: None in technology. The advantage is physical infrastructure - equipment, storage, and railway siding already built inside the port boundary.
A15: Growth Filter
A16: Is revenue growing consistently over 3–5 years? | B16: Yes and accelerating. A jump from 211cr to 336cr in FY 2025 is notable
A17: Is profit growing faster than revenue? | B17: Yes significantly. Revenue CAGR 3yr = 21%, Profit CAGR 3yr = 107%. Profit growing 5x faster than revenue - exceptional operating leverage.
A18: What's driving growth? volume, price, new customers, or just accounting? | B18: India's coal import volumes through east coast ports increasing. Fertiliser imports rising. New services added within the port - crusher operations, expanded warehousing. Paradip Port itself is expanding capacity which directly benefits Paradeep Parivahan.
A20: Risks
A21: Is debt dangerously high relative to earnings? | B21: Manageable. Borrowings = 54 Cr, Net Profit TTM = 35 Cr. Debt actually reduced from 75 Cr to 54 Cr. Positive direction.
A22: What breaks this business? | B22: Paradip Port Trust cancels or doesn't renew operational agreement. Coal import volumes falls sharply and Debtor days worsen which will affect CFO.
A24: My Interests
A25: Will this make me money? | B25: Yes - highest probability. PEG is 0.06, highly undervalued. PEG<1 = Undervalued, PEG> 1 = Overvalued.
A26: Is this a good business? | B26: Yes - genuinely good. Port logistics with captive location moat, positive cash flows, and profits doubling every year is a durable business.
A27: If the stock falls 30% after you buy @ CMP, what will you do?:
A28: Sell? Hold? Buy more? | B28: Buy more aggressively.
A29: WHY? | B29: At current price of 140, P/E is already 6.3x. A 30% fall takes price to 98 and P/E to approximately 4.4x. You would be buying a port logistics company with captive moat, 107% profit CAGR, positive cash flows, and stable promoter holding at 4.4x earnings. That is an extraordinary opportunity.

Sheet Silkflex Polymers (India) Ltd
A1: Business Quality
A2: How does the company make money? | B2: Pure trading company. Imports textile printing inks and water-based wood coating polymers from Silkflex Malaysia and distributes them to garment manufacturers and wood furniture companies across India. No manufacturing - they buy finished product from Malaysia and sell it in India with a markup.
A3: Who is the customer? | B3: Garment manufacturers and Furniture manufacturers
A4: Why would the customer choose them over others? | B4: Silkflex Malaysia's products have established quality reputation in global markets - used across India, Thailand, Turkey, Russia, Sri Lanka, Bangladesh, and Indonesia.
A6: Edge
A7: What makes this company different? | B7: Exclusive or preferred distributor relationship with Silkflex Malaysia in India. If this exclusivity is real, competitors cannot source the same product.
A8: Can competitors easily copy this? | B8: Depends entirely on whether the Malaysia distribution agreement is exclusive.
A9: Does it have:
A10: Pricing power? | B10: Improving. Operating margins jumped from 5% to 15-21% recently. This suggests either they negotiated better terms with the Malaysian supplier, or they raised prices successfully, or product mix shifted to higher margin items.
A11: Switching costs? | B11: Moderate. Garment manufacturers who have validated specific ink formulations in their production process resist switching - re-qualification takes time and risks production quality. But if a cheaper alternative ink offers similar quality, switching is possible.
A12: Brand? | B12: Small. The Silkflex brand belongs to the Malaysian company, not the Indian distributor. Silkflex India as a brand has limited independent value.
A13: Tech advantage? | B13: None. Trading someone else's product
A15: Growth Filter
A16: Is revenue growing consistently over 3–5 years? | B16: Yes. Accelerating in recent years
A17: Is profit growing faster than revenue? | B17: Yes dramatically. Revenue CAGR 3yr = 42%, Profit CAGR 3yr = 116%. The recent margin expansion from 5% to 15-21% is driving profit growth far ahead of revenue growth.
A18: What's driving growth? volume, price, new customers, or just accounting? | B18: Volume expansion as more Indian textile and furniture manufacturers adopt Silkflex products. Possibly geographic expansion into new cities.
A20: Risks
A21: Is debt dangerously high relative to earnings? | B21: Yes. Debt is nearly 8x annual profits.
A22: What breaks this business? | B22: Silkflex Malaysia terminates the distribution agreement. CFO stays negative.
A24: My Interests
A25: Will this make me money? | B25: Risky but yes
A26: Is this a good business? | B26: Kind of. Recent margin improvement is interesting
A27: If the stock falls 30% after you buy @ CMP, what will you do?:
A28: Sell? Hold? Buy more? | B28: Sell.
A29: WHY? | B29: The thesis for Silkflex is thin - it rests entirely on recent margin improvement being sustained and manufacturing capex paying off. A 30% fall would likely indicate that either margins are reverting or the cash flow problem is worsening. Since the business has no hard moat to fall back on - no regulatory certification, no captive location, no manufacturing IP - there is nothing to protect you on the downside. Cut the loss and redeploy capital into businesses with clearer, more durable advantages.
