Workbook

Sheet Input
A1: Name of the Company | B1: Alpha Plastics Pvt Ltd
A2: Start of the Business | B2: 45383
A4: Operations
A5: Production Capacity | B5: 100000 | C5: units/year
A6: Capacity Utilization (Year 1) | B6: 0.5 | C6: Percent
A7: Utilization Growth | B7: 0.05 | C7: Percent/year
A8: Units Sold (% of production) | B8: 0.85 | C8: Percent
A10: Selling price | B10: 1200 | C10: Rs
A11: Annual growth rate | B11: 0.06 | C11: Percent
A12: Raw material per unit | B12: 500 | C12: Rs
A13: Labour cost per unit | B13: 250 | C13: Rs
A14: Raw material growth | B14: 0.05 | C14: Percent
A15: Labour cost growth | B15: 0.07 | C15: Percent
A17: Operating Expenses
A18: Fixed SG&A | B18: 2000000 | C18: Rs
A19: Annual growth rate | B19: 0.05 | C19: percent
A20: Sales commission | B20: 0.08 | C20: Percent
A22: Capital Expenditure
A23: Equipment | B23: 2500000 | C23: Rs
A24: Depreciation rate | B24: 0.15 | C24: Percent
A25: Additional Capex | B25: 1000000 | C25: Rs
A27: Debt
A28: Loan | B28: 2000000 | C28: Rs
A29: Interest rate | B29: 0.12 | C29: Percent
A30: Loan Repayment period | B30: 5 | C30: years
A32: Working capital
A33: Debtor days | B33: 45 | C33: Days
A34: Annual reduction in debtor days | B34: 2 | C34: Days
A35: Creditor days | B35: 60 | C35: Days
A36: Annual increase in creditor days | B36: 2 | C36: Days
A37: Inventory days | B37: 50 | C37: Days
A39: Tax rate | B39: 0.3 | C39: percent

Sheet Revenue
A1: Particulars | C1: FY2024 | D1: FY2025 | E1: FY2026 | F1: FY2027 | G1: FY2028 | H1: FY2029
A2: Year endings | D2: =EOMONTH(Input!B2,11) -> 45747 | E2: =EOMONTH(D2,12) -> 46112 | F2: =EOMONTH(E2,12) -> 46477 | G2: =EOMONTH(F2,12) -> 46843 | H2: =EOMONTH(G2,12) -> 47208
A4: Annual production capacity | B4: Units | D4: =Input!$B$5 -> 100000 | E4: =Input!$B$5 -> 100000 | F4: =Input!$B$5 -> 100000 | G4: =Input!$B$5 -> 100000 | H4: =Input!$B$5 -> 100000
A5: Capacity Utilization | B5: Percentage | D5: =MAX(Input!$B$6,Revenue!C5+Input!$B$7) -> 0.5 | E5: =MAX(Input!$B$6,Revenue!D5+Input!$B$7) -> 0.55 | F5: =MAX(Input!$B$6,Revenue!E5+Input!$B$7) -> 0.6 | G5: =MAX(Input!$B$6,Revenue!F5+Input!$B$7) -> 0.65 | H5: =MAX(Input!$B$6,Revenue!G5+Input!$B$7) -> 0.7
A6: Total Production | B6: Units | D6: =D4*D5 -> 50000 | E6: =E4*E5 -> 55000 | F6: =F4*F5 -> 60000 | G6: =G4*G5 -> 65000 | H6: =H4*H5 -> 70000
A8: Units sold (as % of available units) | B8: Percentage | D8: =Input!$B$8 -> 0.85 | E8: =Input!$B$8 -> 0.85 | F8: =Input!$B$8 -> 0.85 | G8: =Input!$B$8 -> 0.85 | H8: =Input!$B$8 -> 0.85
A10: Units available | B10: Units
A11: Opening stock | B11: Units | D11: 0 | E11: =D15 -> 7500 | F11: =E15 -> 9375 | G11: =F15 -> 10406.25 | H11: =G15 -> 11310.938
A12: Add: Production | B12: Units | D12: =D6 -> 50000 | E12: =E6 -> 55000 | F12: =F6 -> 60000 | G12: =G6 -> 65000 | H12: =H6 -> 70000
A13: Available units | B13: Units | D13: =SUM(D11:D12) -> 50000 | E13: =SUM(E11:E12) -> 62500 | F13: =SUM(F11:F12) -> 69375 | G13: =SUM(G11:G12) -> 75406.25 | H13: =SUM(H11:H12) -> 81310.938
A14: Units sold | B14: Units | D14: =D13*D8 -> 42500 | E14: =E13*E8 -> 53125 | F14: =F13*F8 -> 58968.75 | G14: =G13*G8 -> 64095.313 | H14: =H13*H8 -> 69114.297
A15: Closing stock | B15: Units | D15: =D13-D14 -> 7500 | E15: =E13-E14 -> 9375 | F15: =F13-F14 -> 10406.25 | G15: =G13-G14 -> 11310.938 | H15: =H13-H14 -> 12196.641
A17: Selling price per unit | B17: Rs/Unit | D17: =MAX(Input!$B$10,Revenue!C17*(1+Input!$B$11)) -> 1200 | E17: =MAX(Input!$B$10,Revenue!D17*(1+Input!$B$11)) -> 1272 | F17: =MAX(Input!$B$10,Revenue!E17*(1+Input!$B$11)) -> 1348.32 | G17: =MAX(Input!$B$10,Revenue!F17*(1+Input!$B$11)) -> 1429.2192 | H17: =MAX(Input!$B$10,Revenue!G17*(1+Input!$B$11)) -> 1514.9724
A18: Revenue | B18: Rs | D18: =D17*D14 -> 51000000 | E18: =E17*E14 -> 67575000 | F18: =F17*F14 -> 79508745 | G18: =G17*G14 -> 91606251 | H18: =H17*H14 -> 1.0470625e+08
A20: COGS
A21: Cost of production
A22: Material/unit | B22: Rs | D22: =MAX(C22*(1+Input!$B$14),Input!$B$12) -> 500 | E22: =MAX(D22*(1+Input!$B$14),Input!$B$12) -> 525 | F22: =MAX(E22*(1+Input!$B$14),Input!$B$12) -> 551.25 | G22: =MAX(F22*(1+Input!$B$14),Input!$B$12) -> 578.8125 | H22: =MAX(G22*(1+Input!$B$14),Input!$B$12) -> 607.75313
A23: Labour/unit | B23: Rs | D23: =MAX(C23*(1+Input!$B$15),Input!$B$13) -> 250 | E23: =MAX(D23*(1+Input!$B$15),Input!$B$13) -> 267.5 | F23: =MAX(E23*(1+Input!$B$15),Input!$B$13) -> 286.225 | G23: =MAX(F23*(1+Input!$B$15),Input!$B$13) -> 306.26075 | H23: =MAX(G23*(1+Input!$B$15),Input!$B$13) -> 327.699
A25: Opening stock | B25: Rs | D25: =C27 -> 0 | E25: =D27 -> -5625000 | F25: =E27 -> -7429687.5 | G25: =F27 -> -8714974.2 | H25: =G27 -> -10011008
A26: Total cost of production | B26: Rs | D26: =SUM(D22:D23)*D6 -> 37500000 | E26: =SUM(E22:E23)*E6 -> 43587500 | F26: =SUM(F22:F23)*F6 -> 50248500 | G26: =SUM(G22:G23)*G6 -> 57529761 | H26: =SUM(H22:H23)*H6 -> 65481649
A27: Less: Closing stock | B27: Rs | D27: =-SUM(D22:D23)*D15 -> -5625000 | E27: =-SUM(E22:E23)*E15 -> -7429687.5 | F27: =-SUM(F22:F23)*F15 -> -8714974.2 | G27: =-SUM(G22:G23)*G15 -> -10011008 | H27: =-SUM(H22:H23)*H15 -> -11409373
A28: Cost of goods sold | D28: =SUM(D25:D27) -> 31875000 | E28: =SUM(E25:E27) -> 30532813 | F28: =SUM(F25:F27) -> 34103838 | G28: =SUM(G25:G27) -> 38803779 | H28: =SUM(H25:H27) -> 44061267

Sheet P&L
A1: Particulars | D1: FY2025 | E1: FY2026 | F1: FY2027 | G1: FY2028 | H1: FY2029
A2: Year endings | D2: =EOMONTH(Input!B2,11) -> 45747 | E2: =EOMONTH(D2,12) -> 46112 | F2: =EOMONTH(E2,12) -> 46477 | G2: =EOMONTH(F2,12) -> 46843 | H2: =EOMONTH(G2,12) -> 47208
A3: Revenue | B3: Rs | D3: =Revenue!D18 -> 51000000 | E3: =Revenue!E18 -> 67575000 | F3: =Revenue!F18 -> 79508745 | G3: =Revenue!G18 -> 91606251 | H3: =Revenue!H18 -> 1.0470625e+08
A4: Less: COGS | B4: Rs | D4: =Revenue!D28 -> 31875000 | E4: =Revenue!E28 -> 30532813 | F4: =Revenue!F28 -> 34103838 | G4: =Revenue!G28 -> 38803779 | H4: =Revenue!H28 -> 44061267
A5: Gross profit | B5: Rs | D5: =D3-D4 -> 19125000 | E5: =E3-E4 -> 37042188 | F5: =F3-F4 -> 45404907 | G5: =G3-G4 -> 52802472 | H5: =H3-H4 -> 60644982
A6: Less: Indirect cost | B6: Rs
A7: Commission on sales | B7: Rs | D7: =D3*Input!$B$20 -> 4080000 | E7: =E3*Input!$B$20 -> 5406000 | F7: =F3*Input!$B$20 -> 6360699.6 | G7: =G3*Input!$B$20 -> 7328500.1 | H7: =H3*Input!$B$20 -> 8376499.9
A8: SG&A | B8: Rs | D8: =MAX(Input!$B$18,'P&L'!C8*(1+Input!$B$19)) -> 2000000 | E8: =MAX(Input!$B$18,'P&L'!D8*(1+Input!$B$19)) -> 2100000 | F8: =MAX(Input!$B$18,'P&L'!E8*(1+Input!$B$19)) -> 2205000 | G8: =MAX(Input!$B$18,'P&L'!F8*(1+Input!$B$19)) -> 2315250 | H8: =MAX(Input!$B$18,'P&L'!G8*(1+Input!$B$19)) -> 2431012.5
A9: Total Indirect cost | B9: Rs | D9: =SUM(D6:D8) -> 6080000 | E9: =SUM(E6:E8) -> 7506000 | F9: =SUM(F6:F8) -> 8565699.6 | G9: =SUM(G6:G8) -> 9643750.1 | H9: =SUM(H6:H8) -> 10807512
A10: EBITDA | B10: Rs | D10: =D5-D9 -> 13045000 | E10: =E5-E9 -> 29536188 | F10: =F5-F9 -> 36839207 | G10: =G5-G9 -> 43158722 | H10: =H5-H9 -> 49837469
A11: Less: Dep. And Amortization | B11: Rs | D11: ='Fixed assets'!D10 -> 375000 | E11: ='Fixed assets'!E10 -> 375000 | F11: ='Fixed assets'!F10 -> 525000 | G11: ='Fixed assets'!G10 -> 525000 | H11: ='Fixed assets'!H10 -> 525000
A12: EBIT | B12: Rs | D12: =D10-D11 -> 12670000 | E12: =E10-E11 -> 29161188 | F12: =F10-F11 -> 36314207 | G12: =G10-G11 -> 42633722 | H12: =H10-H11 -> 49312469
A13: Less: Interest expenses | B13: Rs | D13: ='Debt schedule'!D7 -> 240000 | E13: ='Debt schedule'!E7 -> 192000 | F13: ='Debt schedule'!F7 -> 144000 | G13: ='Debt schedule'!G7 -> 96000 | H13: ='Debt schedule'!H7 -> 48000
A14: EBT | B14: Rs | D14: =D12-D13 -> 12430000 | E14: =E12-E13 -> 28969188 | F14: =F12-F13 -> 36170207 | G14: =G12-G13 -> 42537722 | H14: =H12-H13 -> 49264469
A15: Less: Income Tax | B15: Rs | D15: =D14*Input!$B$39 -> 3729000 | E15: =E14*Input!$B$39 -> 8690756.3 | F15: =F14*Input!$B$39 -> 10851062 | G15: =G14*Input!$B$39 -> 12761317 | H15: =H14*Input!$B$39 -> 14779341
A16: Net Income | B16: Rs | D16: =D14-D15 -> 8701000 | E16: =E14-E15 -> 20278431 | F16: =F14-F15 -> 25319145 | G16: =G14-G15 -> 29776406 | H16: =H14-H15 -> 34485128

Sheet Fixed assets
A1: Particulars | D1: FY2025 | E1: FY2026 | F1: FY2027 | G1: FY2028 | H1: FY2029
A2: Year endings | D2: =EOMONTH(Input!B2,11) -> 45747 | E2: =EOMONTH(D2,12) -> 46112 | F2: =EOMONTH(E2,12) -> 46477 | G2: =EOMONTH(F2,12) -> 46843 | H2: =EOMONTH(G2,12) -> 47208
A3: Equipment
A4: Opening balance | B4: Rs | D4: =C7 -> 0 | E4: =D7 -> 2500000 | F4: =E7 -> 2500000 | G4: =F7 -> 3500000 | H4: =G7 -> 3500000
A5: Add: Purchases | B5: Rs | D5: =Input!$B$23 -> 2500000 | E5: 0 | F5: =Input!$B$25 -> 1000000 | G5: 0 | H5: 0
A6: Less: Sales | B6: Rs | D6: 0 | E6: 0 | F6: 0 | G6: 0 | H6: 0
A7: Gross block | B7: Rs | D7: =D4+D5-D6 -> 2500000 | E7: =E4+E5-E6 -> 2500000 | F7: =F4+F5-F6 -> 3500000 | G7: =G4+G5-G6 -> 3500000 | H7: =H4+H5-H6 -> 3500000
A8: Less: Accumulated depeciation | B8: Rs | D8: =D7*Input!$B$24 -> 375000 | E8: =E7*Input!$B$24+D8 -> 750000 | F8: =F7*Input!$B$24+E8 -> 1275000 | G8: =G7*Input!$B$24+F8 -> 1800000 | H8: =H7*Input!$B$24+G8 -> 2325000
A9: Net block | B9: Rs | D9: =D7-D8 -> 2125000 | E9: =E7-E8 -> 1750000 | F9: =F7-F8 -> 2225000 | G9: =G7-G8 -> 1700000 | H9: =H7-H8 -> 1175000
A10: Depreciation for the year | B10: Rs | D10: =D8-C8 -> 375000 | E10: =E8-D8 -> 375000 | F10: =F8-E8 -> 525000 | G10: =G8-F8 -> 525000 | H10: =H8-G8 -> 525000

Sheet Debt schedule
A1: Particulars | D1: FY2025 | E1: FY2026 | F1: FY2027 | G1: FY2028 | H1: FY2029
A2: Year endings | D2: =EOMONTH(Input!B2,11) -> 45747 | E2: =EOMONTH(D2,12) -> 46112 | F2: =EOMONTH(E2,12) -> 46477 | G2: =EOMONTH(F2,12) -> 46843 | H2: =EOMONTH(G2,12) -> 47208
A3: Opening loan | D3: =Input!$B$28 -> 2000000 | E3: =D5 -> 1600000 | F3: =E5 -> 1200000 | G3: =F5 -> 800000 | H3: =G5 -> 400000
A4: Less: Principal repayment | D4: =Input!$B$28/Input!$B$30 -> 400000 | E4: =Input!$B$28/Input!$B$30 -> 400000 | F4: =Input!$B$28/Input!$B$30 -> 400000 | G4: =Input!$B$28/Input!$B$30 -> 400000 | H4: =Input!$B$28/Input!$B$30 -> 400000
A5: Closing balance | D5: =D3-D4 -> 1600000 | E5: =E3-E4 -> 1200000 | F5: =F3-F4 -> 800000 | G5: =G3-G4 -> 400000 | H5: =H3-H4 -> 0
A7: Interest expenses | D7: =D3*Input!$B$29 -> 240000 | E7: =E3*Input!$B$29 -> 192000 | F7: =F3*Input!$B$29 -> 144000 | G7: =G3*Input!$B$29 -> 96000 | H7: =H3*Input!$B$29 -> 48000

Sheet Working capital
A1: Particulars | D1: FY2025 | E1: FY2026 | F1: FY2027 | G1: FY2028 | H1: FY2029
A2: Year endings | D2: =EOMONTH(Input!B2,11) -> 45747 | E2: =EOMONTH(D2,12) -> 46112 | F2: =EOMONTH(E2,12) -> 46477 | G2: =EOMONTH(F2,12) -> 46843 | H2: =EOMONTH(G2,12) -> 47208
A3: Current Assets
A4: Debtors | D4: ='P&L'!D3/365*'Working capital'!D5 -> 6287671.2 | E4: ='P&L'!E3/365*'Working capital'!E5 -> 7960890.4 | F4: ='P&L'!F3/365*'Working capital'!F5 -> 8931119.3 | G4: ='P&L'!G3/365*'Working capital'!G5 -> 9788065.2 | H4: ='P&L'!H3/365*'Working capital'!H5 -> 10614058
A5: Debtors days | D5: =Input!$B$33 -> 45 | E5: =D5-2 -> 43 | F5: =E5-2 -> 41 | G5: =F5-2 -> 39 | H5: =G5-2 -> 37
A6: Inventory | D6: =Revenue!D15*(Revenue!D22+Revenue!D23) -> 5625000 | E6: =Revenue!E15*(Revenue!E22+Revenue!E23) -> 7429687.5 | F6: =Revenue!F15*(Revenue!F22+Revenue!F23) -> 8714974.2 | G6: =Revenue!G15*(Revenue!G22+Revenue!G23) -> 10011008 | H6: =Revenue!H15*(Revenue!H22+Revenue!H23) -> 11409373
A7: Inventory days | D7: =Input!$B$37 -> 50 | E7: =Input!$B$37 -> 50 | F7: =Input!$B$37 -> 50 | G7: =Input!$B$37 -> 50 | H7: =Input!$B$37 -> 50
A9: Current Liabilities
A10: Creditors | D10: ='P&L'!D4/365*'Working capital'!D11 -> 5239726 | E10: ='P&L'!E4/365*'Working capital'!E11 -> 5186395.5 | F10: ='P&L'!F4/365*'Working capital'!F11 -> 5979851.1 | G10: ='P&L'!G4/365*'Working capital'!G11 -> 7016573.7 | H10: ='P&L'!H4/365*'Working capital'!H11 -> 8208674.5
A11: Creditor days | D11: =Input!$B$35 -> 60 | E11: =D11+2 -> 62 | F11: =E11+2 -> 64 | G11: =F11+2 -> 66 | H11: =G11+2 -> 68
A12: Net working capital | D12: =D4+D6-D10 -> 6672945.2 | E12: =E4+E6-E10 -> 10204182 | F12: =F4+F6-F10 -> 11666242 | G12: =G4+G6-G10 -> 12782500 | H12: =H4+H6-H10 -> 13814757
A14: Change in Working Capital | D14: 0 | E14: =E12-D12 -> 3531237.2 | F14: =F12-E12 -> 1462060.1 | G14: =G12-F12 -> 1116257.3 | H14: =H12-G12 -> 1032257.4

Sheet Cashflow Statement
A1: Particulars | D1: FY2025 | E1: FY2026 | F1: FY2027 | G1: FY2028 | H1: FY2029
A2: Year endings | D2: =EOMONTH(Input!B2,11) -> 45747 | E2: =EOMONTH(D2,12) -> 46112 | F2: =EOMONTH(E2,12) -> 46477 | G2: =EOMONTH(F2,12) -> 46843 | H2: =EOMONTH(G2,12) -> 47208
A3: Cashflow from Operating activities
A4: Net income | D4: ='P&L'!D16 -> 8701000 | E4: ='P&L'!E16 -> 20278431 | F4: ='P&L'!F16 -> 25319145 | G4: ='P&L'!G16 -> 29776406 | H4: ='P&L'!H16 -> 34485128
A5: Add: Depreciation | D5: ='Fixed assets'!D10 -> 375000 | E5: ='Fixed assets'!E10 -> 375000 | F5: ='Fixed assets'!F10 -> 525000 | G5: ='Fixed assets'!G10 -> 525000 | H5: ='Fixed assets'!H10 -> 525000
A6: Add: Interest expenses | D6: ='P&L'!D13 -> 240000 | E6: ='P&L'!E13 -> 192000 | F6: ='P&L'!F13 -> 144000 | G6: ='P&L'!G13 -> 96000 | H6: ='P&L'!H13 -> 48000
A7: Cashflow from Operations before impact of working capital | D7: =SUM(D4:D6) -> 9316000 | E7: =SUM(E4:E6) -> 20845431 | F7: =SUM(F4:F6) -> 25988145 | G7: =SUM(G4:G6) -> 30397406 | H7: =SUM(H4:H6) -> 35058128
A8: Changes in Debtors | D8: =-('Balance sheet'!D23)-'Balance sheet'!C23 -> -6287671.2 | E8: =-('Balance sheet'!E23)+('Balance sheet'!D23) -> -1673219.2 | F8: =-('Balance sheet'!F23)+('Balance sheet'!E23) -> -970228.89 | G8: =-('Balance sheet'!G23)+('Balance sheet'!F23) -> -856945.9 | H8: =-('Balance sheet'!H23)+('Balance sheet'!G23) -> -825992.9
A9: Changes in Inventory | D9: =-('Balance sheet'!D24) -> -5625000 | E9: =-('Balance sheet'!E24)+('Balance sheet'!D24) -> -1804687.5 | F9: =-('Balance sheet'!F24)+('Balance sheet'!E24) -> -1285286.7 | G9: =-('Balance sheet'!G24)+('Balance sheet'!F24) -> -1296034 | H9: =-('Balance sheet'!H24)+('Balance sheet'!G24) -> -1398365.2
A10: Changes in Creditors | D10: ='Working capital'!D10-'Working capital'!C10 -> 5239726 | E10: ='Working capital'!E10-'Working capital'!D10 -> -53330.479 | F10: ='Working capital'!F10-'Working capital'!E10 -> 793455.55 | G10: ='Working capital'!G10-'Working capital'!F10 -> 1036722.6 | H10: ='Working capital'!H10-'Working capital'!G10 -> 1192100.8
A11: Cashflow from operations | D11: =SUM(D7:D10) -> 2643054.8 | E11: =SUM(E7:E10) -> 17314194 | F11: =SUM(F7:F10) -> 24526085 | G11: =SUM(G7:G10) -> 29281148 | H11: =SUM(H7:H10) -> 34025871
A13: Cashflow from Investing activities
A14: Purchases:
A15: Equipment | D15: =-('Fixed assets'!D5) -> -2500000 | E15: =-('Fixed assets'!E5) -> 0 | F15: =-('Fixed assets'!F5) -> -1000000 | G15: =-('Fixed assets'!G5) -> 0 | H15: =-('Fixed assets'!H5) -> 0
A16: Cashflow from Investing activities | D16: =SUM(D15) -> -2500000 | E16: =SUM(E15) -> 0 | F16: =SUM(F15) -> -1000000 | G16: =SUM(G15) -> 0 | H16: =SUM(H15) -> 0
A18: Cashflow from Financing activities
A19: Equity | D19: ='Balance sheet'!D4-'Balance sheet'!C4 -> 500000 | E19: ='Balance sheet'!E4-'Balance sheet'!D4 -> 0 | F19: ='Balance sheet'!F4-'Balance sheet'!E4 -> 0 | G19: ='Balance sheet'!G4-'Balance sheet'!F4 -> 0 | H19: ='Balance sheet'!H4-'Balance sheet'!G4 -> 0
A20: Debt taken | D20: ='Debt schedule'!D3 -> 2000000 | E20: 0 | F20: 0 | G20: 0 | H20: 0
A21: Debt repaid | D21: =-'Debt schedule'!D4 -> -400000 | E21: =-'Debt schedule'!E4 -> -400000 | F21: =-'Debt schedule'!F4 -> -400000 | G21: =-'Debt schedule'!G4 -> -400000 | H21: =-'Debt schedule'!H4 -> -400000
A23: Cashflow from Financing activities | D23: =SUM(D19:D22) -> 2100000 | E23: =SUM(E19:E22) -> -400000 | F23: =SUM(F19:F22) -> -400000 | G23: =SUM(G19:G22) -> -400000 | H23: =SUM(H19:H22) -> -400000
A25: Net cashflow | D25: =SUM(D11,D16,D23) -> 2243054.8 | E25: =SUM(E11,E16,E23) -> 16914194 | F25: =SUM(F11,F16,F23) -> 23126085 | G25: =SUM(G11,G16,G23) -> 28881148 | H25: =SUM(H11,H16,H23) -> 33625871
A26: Cash | D26: =D25+C26 -> 2243054.8 | E26: =E25+D26 -> 19157249 | F26: =F25+E26 -> 42283334 | G26: =G25+F26 -> 71164482 | H26: =H25+G26 -> 1.0479035e+08

Sheet Balance sheet
A1: Particulars | D1: FY2025 | E1: FY2026 | F1: FY2027 | G1: FY2028 | H1: FY2029
A2: Year endings | D2: =EOMONTH(Input!B2,11) -> 45747 | E2: =EOMONTH(D2,12) -> 46112 | F2: =EOMONTH(E2,12) -> 46477 | G2: =EOMONTH(F2,12) -> 46843 | H2: =EOMONTH(G2,12) -> 47208
A3: Equity
A4: Share capital | D4: =Input!$B$23-Input!$B$18 -> 500000 | E4: =Input!$B$23-Input!$B$18 -> 500000 | F4: =Input!$B$23-Input!$B$18 -> 500000 | G4: =Input!$B$23-Input!$B$18 -> 500000 | H4: =Input!$B$23-Input!$B$18 -> 500000
A5: Retained earnings | D5: =D27-D14-D4 -> 8941000 | E5: =E27-E14-E4 -> 29411431 | F5: =F27-F14-F4 -> 54874576 | G5: =G27-G14-G4 -> 84746982 | H5: =H27-H14-H4 -> 1.1928011e+08
A6: Total equity | D6: =SUM(D4:D5) -> 9441000 | E6: =SUM(E4:E5) -> 29911431 | F6: =SUM(F4:F5) -> 55374576 | G6: =SUM(G4:G5) -> 85246982 | H6: =SUM(H4:H5) -> 1.1978011e+08
A8: Liabilities
A9: Non-current liabilities
A10: Loan from bank | D10: ='Debt schedule'!D5 -> 1600000 | E10: ='Debt schedule'!E5 -> 1200000 | F10: ='Debt schedule'!F5 -> 800000 | G10: ='Debt schedule'!G5 -> 400000 | H10: ='Debt schedule'!H5 -> 0
A12: Current liabilities
A13: Creditors + Loan | D13: ='Working capital'!D10 -> 5239726 | E13: ='Working capital'!E10 -> 5186395.5 | F13: ='Working capital'!F10 -> 5979851.1 | G13: ='Working capital'!G10 -> 7016573.7 | H13: ='Working capital'!H10 -> 8208674.5
A14: Total Liabilities | D14: =SUM(D13,D10) -> 6839726 | E14: =SUM(E13,E10) -> 6386395.5 | F14: =SUM(F13,F10) -> 6779851.1 | G14: =SUM(G13,G10) -> 7416573.7 | H14: =SUM(H13,H10) -> 8208674.5
A15: Total (Liabilities & Equities) | D15: =SUM(D13,D10,D6) -> 16280726 | E15: =SUM(E13,E10,E6) -> 36297827 | F15: =SUM(F13,F10,F6) -> 62154427 | G15: =SUM(G13,G10,G6) -> 92663556 | H15: =SUM(H13,H10,H6) -> 1.2798878e+08
A17: Assets
A18: Non-current assets
A19: Fixed assets
A20: Equipments | D20: ='Fixed assets'!D9 -> 2125000 | E20: ='Fixed assets'!E9 -> 1750000 | F20: ='Fixed assets'!F9 -> 2225000 | G20: ='Fixed assets'!G9 -> 1700000 | H20: ='Fixed assets'!H9 -> 1175000
A22: Current assets
A23: Debtors | D23: ='Working capital'!D4 -> 6287671.2 | E23: ='Working capital'!E4 -> 7960890.4 | F23: ='Working capital'!F4 -> 8931119.3 | G23: ='Working capital'!G4 -> 9788065.2 | H23: ='Working capital'!H4 -> 10614058
A24: Inventory | D24: ='Working capital'!D6 -> 5625000 | E24: ='Working capital'!E6 -> 7429687.5 | F24: ='Working capital'!F6 -> 8714974.2 | G24: ='Working capital'!G6 -> 10011008 | H24: ='Working capital'!H6 -> 11409373
A25: Cash | D25: ='Cashflow Statement'!D26 -> 2243054.8 | E25: ='Cashflow Statement'!E26 -> 19157249 | F25: ='Cashflow Statement'!F26 -> 42283334 | G25: ='Cashflow Statement'!G26 -> 71164482 | H25: ='Cashflow Statement'!H26 -> 1.0479035e+08
A27: Total assets | D27: =SUM(D23:D25,D20) -> 16280726 | E27: =SUM(E23:E25,E20) -> 36297827 | F27: =SUM(F23:F25,F20) -> 62154427 | G27: =SUM(G23:G25,G20) -> 92663556 | H27: =SUM(H23:H25,H20) -> 1.2798878e+08
A28: Check | D28: =D27-D15 -> 0 | E28: =E27-E15 -> 0 | F28: =F27-F15 -> 0 | G28: =G27-G15 -> 0 | H28: =H27-H15 -> 0

Sheet Sheet1

Sheet Free Cashflows
A1: Particulars | D1: FY2025 | E1: FY2026 | F1: FY2027 | G1: FY2028 | H1: FY2029
A2: Year endings | D2: =EOMONTH(Input!B2,11) -> 45747 | E2: =EOMONTH(D2,12) -> 46112 | F2: =EOMONTH(E2,12) -> 46477 | G2: =EOMONTH(F2,12) -> 46843 | H2: =EOMONTH(G2,12) -> 47208
A3: Free cashflow calculation
A4: EBIT | B4: Rs. | D4: ='P&L'!D12 -> 12670000 | E4: ='P&L'!E12 -> 29161188 | F4: ='P&L'!F12 -> 36314207 | G4: ='P&L'!G12 -> 42633722 | H4: ='P&L'!H12 -> 49312469
A5: Less: Tax | B5: Rs. | D5: =D4*Input!$B$39 -> 3801000 | E5: =E4*Input!$B$39 -> 8748356.3 | F5: =F4*Input!$B$39 -> 10894262 | G5: =G4*Input!$B$39 -> 12790117 | H5: =H4*Input!$B$39 -> 14793741
A6: NOPAT | B6: Rs. | D6: =D4-D5 -> 8869000 | E6: =E4-E5 -> 20412831 | F6: =F4-F5 -> 25419945 | G6: =G4-G5 -> 29843606 | H6: =H4-H5 -> 34518728
A7: Add: Depreciations | B7: Rs. | D7: ='P&L'!D11 -> 375000 | E7: ='P&L'!E11 -> 375000 | F7: ='P&L'!F11 -> 525000 | G7: ='P&L'!G11 -> 525000 | H7: ='P&L'!H11 -> 525000
A8: Less: Capital expenditure | B8: Rs. | D8: ='Cashflow Statement'!D15 -> -2500000 | E8: ='Cashflow Statement'!E15 -> 0 | F8: ='Cashflow Statement'!F15 -> -1000000 | G8: ='Cashflow Statement'!G15 -> 0 | H8: ='Cashflow Statement'!H15 -> 0
A9: Less: Change in working capital | B9: Rs. | D9: =SUM('Cashflow Statement'!D8:D10) -> -6672945.2 | E9: =SUM('Cashflow Statement'!E8:E10) -> -3531237.2 | F9: =SUM('Cashflow Statement'!F8:F10) -> -1462060.1 | G9: =SUM('Cashflow Statement'!G8:G10) -> -1116257.3 | H9: =SUM('Cashflow Statement'!H8:H10) -> -1032257.4
A10: Free cashflow to Firm (FCFF) | B10: Rs. | D10: =SUM(D6:D9) -> 71054.795 | E10: =SUM(E6:E9) -> 17256594 | F10: =SUM(F6:F9) -> 23482885 | G10: =SUM(G6:G9) -> 29252348 | H10: =SUM(H6:H9) -> 34011471
A11: Less: Interest after tax | B11: Rs. | D11: =-'P&L'!D13*(1-Input!$B$39) -> -168000 | E11: =-'P&L'!E13*(1-Input!$B$39) -> -134400 | F11: =-'P&L'!F13*(1-Input!$B$39) -> -100800 | G11: =-'P&L'!G13*(1-Input!$B$39) -> -67200 | H11: =-'P&L'!H13*(1-Input!$B$39) -> -33600
A12: Add/Less: Debt taken/paid | B12: Rs. | D12: =SUM('Cashflow Statement'!D20:D21) -> 1600000 | E12: =SUM('Cashflow Statement'!E20:E21) -> -400000 | F12: =SUM('Cashflow Statement'!F20:F21) -> -400000 | G12: =SUM('Cashflow Statement'!G20:G21) -> -400000 | H12: =SUM('Cashflow Statement'!H20:H21) -> -400000
A13: Free cashflow to Equity (FCFE) | B13: Rs. | D13: =SUM(D10:D12) -> 1503054.8 | E13: =SUM(E10:E12) -> 16722194 | F13: =SUM(F10:F12) -> 22982085 | G13: =SUM(G10:G12) -> 28785148 | H13: =SUM(H10:H12) -> 33577871
